codde_protocol_client-0.1.3.dist-info/METADATA
codde_protocol_client-0.1.3.dist-info/WHEEL
codde_protocol_client-0.1.3.dist-info/license_files/LICENSE
codde_protocol/__init__.py
codde_protocol/codde_protocol.abi3.so
codde_protocol_client-0.1.3.dist-info/RECORD
