Metadata-Version: 2.3
Name: codde_protocol_client
Version: 0.1.3
License-File: LICENSE
Summary: Multi Communication protocol in heart of the C.O.D.D.E. Pi framework
Keywords: rust,python,codde_pi,iot
Home-Page: https://github.com/codde-pi/codde_protocol
Author: Mathis Lecomte <vm.lecomte@gmail.com>
Author-email: Mathis Lecomte <vm.lecomte@gmail.com>
